{
    "size": { "w": 256, "h": 256 },
    "bgColor": { "r": 255, "g": 255, "b": 255 },
    "handsUnit": {
        "hHand": {
            "shape": { "d": -10, "w": 5, "h": 90 },
            "foreground": { "r":   0, "g":   0, "b":   0 },
            "background": { "r": 255, "g": 255, "b": 255 }
        },
        "mHand": {
            "shape": { "d": -10, "w": 4, "h": 110 },
            "foreground": { "r":   0, "g":   0, "b":   0 },
            "background": { "r": 255, "g": 255, "b": 255 }
        },
        "sHand": {
            "shape": { "d": -10, "w": 3, "h": 130 },
            "foreground": { "r":   0, "g":   0, "b":   0 },
            "background": { "r": 255, "g": 255, "b": 255 }
        }
    },
    "signsUnit": {
        "large": {
            "shape": { "d": 80, "w": 5, "h": 20 },
            "foreground": { "r":   0, "g":   0, "b":   0 },
            "background": { "r": 255, "g": 255, "b": 255 }
        },
        "small": {
            "shape": { "d": 90, "w": 3, "h": 10 },
            "foreground": { "r":   0, "g":   0, "b":   0 },
            "background": { "r": 255, "g": 255, "b": 255 }
        }
    }
}
